google_places_scraper/__init__.py
google_places_scraper/cli.py
google_places_scraper/scraper.py
google_places_scraper-0.1.3.dist-info/licenses/LICENSE
google_places_scraper-0.1.3.dist-info/METADATA
google_places_scraper-0.1.3.dist-info/WHEEL
google_places_scraper-0.1.3.dist-info/entry_points.txt
google_places_scraper-0.1.3.dist-info/top_level.txt
google_places_scraper-0.1.3.dist-info/RECORD
