Metadata-Version: 2.4
Name: google-places-scraper
Version: 0.1.3
Summary: A wrapper to scrape Google Places API with logging and export support
Author: Muhammad Arsalan
Author-email: arsalan.9798@gmail.com
License: MIT
Classifier: Programming Language :: Python :: 3
Classifier: License :: OSI Approved :: MIT License
Classifier: Operating System :: OS Independent
Requires-Python: >=3.7
License-File: LICENSE
Requires-Dist: requests
Requires-Dist: pandas
Requires-Dist: pyyaml
Requires-Dist: geopy
Dynamic: author
Dynamic: author-email
Dynamic: classifier
Dynamic: description
Dynamic: description-content-type
Dynamic: license
Dynamic: license-file
Dynamic: requires-dist
Dynamic: requires-python
Dynamic: summary
